{"146268":{"name":"Nicosia","country":"Cyprus","iso2":"CY"},"264371":{"name":"Athens","country":"Greece","iso2":"GR"},"456172":{"name":"Riga","country":"Latvia","iso2":"LV"},"588409":{"name":"Tallinn","country":"Estonia","iso2":"EE"},"593116":{"name":"Vilnius","country":"Lithuania","iso2":"LT"},"658226":{"name":"Helsinki","country":"Finland","iso2":"FI"},"683506":{"name":"Bucharest","country":"Romania","iso2":"RO"},"727011":{"name":"Sofia","country":"Bulgaria","iso2":"BG"},"728193":{"name":"Plovdiv","country":"Bulgaria","iso2":"BG"},"756135":{"name":"Warsaw","country":"Poland","iso2":"PL"},"2267057":{"name":"Lisbon","country":"Portugal","iso2":"PT"},"2411586":{"name":"Gibraltar","country":"Gibraltar","iso2":"GI"},"2562305":{"name":"Valletta","country":"Malta","iso2":"MT"},"2618425":{"name":"Copenhagen","country":"Denmark","iso2":"DK"},"2643743":{"name":"London","country":"United Kingdom of Great Britain and Northern Ireland","iso2":"GB"},"2673730":{"name":"Stockholm","country":"Sweden","iso2":"SE"},"2759794":{"name":"Amsterdam","country":"Netherlands","iso2":"NL"},"2761369":{"name":"Vienna","country":"Austria","iso2":"AT"},"2800866":{"name":"Brussels","country":"Belgium","iso2":"BE"},"2950159":{"name":"Berlin","country":"Germany","iso2":"DE"},"2960316":{"name":"Luxembourg","country":"Luxembourg","iso2":"LU"},"2964574":{"name":"Dublin","country":"Ireland","iso2":"IE"},"3054643":{"name":"Budapest","country":"Hungary","iso2":"HU"},"3060972":{"name":"Bratislava","country":"Slovakia","iso2":"SK"},"3067696":{"name":"Prague","country":"Czech Republic","iso2":"CZ"},"3186886":{"name":"Zagreb","country":"Croatia","iso2":"HR"},"3196359":{"name":"Ljubljana","country":"Slovenia","iso2":"SI"},"6359304":{"name":"Madrid","country":"Spain","iso2":"ES"},"6455259":{"name":"Paris","country":"France","iso2":"FR"}}